pyskell/__init__.py
pyskell/pyskell.py
pyskell-0.0.1.dist-info/LICENSE
pyskell-0.0.1.dist-info/METADATA
pyskell-0.0.1.dist-info/WHEEL
pyskell-0.0.1.dist-info/top_level.txt
pyskell-0.0.1.dist-info/RECORD
