Metadata-Version: 2.1
Name: pyskell
Version: 0.0.1
Summary: # Stuck with Python but you actually want to use Haskell?
Home-page: https://github.com/JohannesMessner/pyskell
Author: Johannes Messner
Author-email: messnerjo@gmail.com
License: UNKNOWN
Project-URL: Bug Tracker, https://github.com/JohannesMessner/pyskell/issues
Platform: UNKNOWN
Classifier: Programming Language :: Python :: 3
Classifier: License :: OSI Approved :: MIT License
Classifier: Operating System :: OS Independent
Requires-Python: >=3.6
License-File: LICENSE
